restit/__init__.py
restit/_path_parameter.py
restit/_response.py
restit/common.py
restit/development_server.py
restit/hyperlink.py
restit/namespace.py
restit/request.py
restit/request_deserializer.py
restit/resource.py
restit/response_serializer.py
restit/restit_app.py
restit/restit_test_app.py
restit/rfc7807_schema.py
restit/static_directory_resource.py
restit/static_file_response.py
restit/decorator/__init__.py
restit/decorator/exception_mapping_decorator.py
restit/decorator/path_decorator.py
restit/decorator/path_parameter_decorator.py
restit/decorator/query_parameter_decorator.py
restit/decorator/request_body_decorator.py
restit/decorator/response_decorator.py
restit/exception/__init__.py
restit/exception/client_errors_4xx.py
restit/exception/http_error.py
restit/exception/http_error_css.py
restit/exception/redirection_messages_3xx.py
restit/exception/server_errors_5xx.py
restit/internal/__init__.py
restit/internal/default_favicon_resource.py
restit/internal/forwarded_header.py
restit/internal/http_accept.py
restit/internal/http_error_response_maker.py
restit/internal/mime_type.py
restit/internal/query_parameter.py
restit/internal/request_body_properties.py
restit/internal/request_body_schema_deserializer.py
restit/internal/request_deserializer_service.py
restit/internal/resource_path.py
restit/internal/response_serializer_service.py
restit/internal/response_status_parameter.py
restit/internal/schema_or_field_deserializer.py
restit/internal/suffix_media_type_mapping.py
restit/internal/typed_body.py
restit/internal/default_request_deserializer/__init__.py
restit/internal/default_request_deserializer/default_application_json_dict_deserializer.py
restit/internal/default_request_deserializer/default_fallback_dict_deserializer.py
restit/internal/default_request_deserializer/default_form_data_dict_deserializer.py
restit/internal/default_response_serializer/__init__.py
restit/internal/default_response_serializer/any_type_json_response_serializer.py
restit-0.3.2.dist-info/LICENSE
restit-0.3.2.dist-info/METADATA
restit-0.3.2.dist-info/WHEEL
restit-0.3.2.dist-info/top_level.txt
restit-0.3.2.dist-info/RECORD
