Metadata-Version: 2.1
Name: restit
Version: 0.3.2
Summary: HTTP REST library including OOP-readiness and Open-API generation
Home-page: https://restit.readthedocs.io/en/latest/
Author: Erik Tuerke
License: UNKNOWN
Platform: UNKNOWN
Classifier: Development Status :: 3 - Alpha
Classifier: Intended Audience :: Developers
Classifier: License :: OSI Approved :: MIT License
Classifier: Programming Language :: Python :: 3.6
Classifier: Programming Language :: Python :: 3.7
Classifier: Programming Language :: Python :: 3.8
Classifier: Programming Language :: Python :: 3.9
Classifier: Programming Language :: Python :: 3.10
License-File: LICENSE
Requires-Dist: marshmallow
